odoo/addons/animal_prescription/README.rst
odoo/addons/animal_prescription/__init__.py
odoo/addons/animal_prescription/__manifest__.py
odoo/addons/animal_prescription/data/physiology.csv
odoo/addons/animal_prescription/data/settings.xml
odoo/addons/animal_prescription/i18n/animal_prescription.pot
odoo/addons/animal_prescription/models/__init__.py
odoo/addons/animal_prescription/models/physiology.py
odoo/addons/animal_prescription/models/posology.py
odoo/addons/animal_prescription/models/sale.py
odoo/addons/animal_prescription/models/sale_line.py
odoo/addons/animal_prescription/readme/DESCRIPTION.rst
odoo/addons/animal_prescription/security/ir.model.access.csv
odoo/addons/animal_prescription/static/description/icon.png
odoo/addons/animal_prescription/static/description/index.html
odoo/addons/animal_prescription/views/herd.xml
odoo/addons/animal_prescription/views/physiology.xml
odoo/addons/animal_prescription/views/product.xml
odoo/addons/animal_prescription/views/sale.xml
odoo14_addon_animal_prescription-14.0.1.0.1.dist-info/METADATA
odoo14_addon_animal_prescription-14.0.1.0.1.dist-info/WHEEL
odoo14_addon_animal_prescription-14.0.1.0.1.dist-info/top_level.txt
odoo14_addon_animal_prescription-14.0.1.0.1.dist-info/RECORD
